setup.py
wikitables/__init__.py
wikitables/client.py
wikitables/models.py
wikitables/util.py
wikitables/version.py
wikitables_for_distll.egg-info/PKG-INFO
wikitables_for_distll.egg-info/SOURCES.txt
wikitables_for_distll.egg-info/dependency_links.txt
wikitables_for_distll.egg-info/requires.txt
wikitables_for_distll.egg-info/top_level.txt