Metadata-Version: 1.1
Name: wikitables-for-distll
Version: 0.0.1
Summary: Import tables from any Wikipedia article fork, fixes python 2.7.10 crashes
Home-page: https://github.com/lucasSimonelli/wikitables
Author: Lucas Simonelli
Author-email: bradley.cicenas@gmail.com
License: http://opensource.org/licenses/MIT
Keywords: wikipedia data
Platform: UNKNOWN
Classifier: Natural Language :: English
Classifier: Programming Language :: Python
Classifier: Intended Audience :: Developers
Classifier: Programming Language :: Python :: 2
Classifier: Programming Language :: Python :: 3
Classifier: License :: OSI Approved :: MIT License 
